CHANGELOG.md
qlikflow/init.py
qlikflow/qlikflow.py
qlikflow/version.py
qlikflow-1.0.14.dist-info/LICENSE
qlikflow-1.0.14.dist-info/WHEEL
qlikflow-1.0.14.dist-info/METADATA
qlikflow-1.0.14.dist-info/RECORD
