Metadata-Version: 2.1
Name: qlikflow
Version: 1.0.14
Summary: This module allows you to create simple Apache Airflow DAG files-constructors for QlikView, Qlik Sense and NPrinting.
Home-page: https://github.com/bintocher/qlikflow
License: Apache-2.0
Author: bintocher
Author-email: schernov1@gmail.com
Requires-Python: >=3.6,<4.0
Classifier: License :: OSI Approved :: Apache Software License
Classifier: Programming Language :: Python :: 3
Classifier: Programming Language :: Python :: 3.6
Classifier: Programming Language :: Python :: 3.7
Classifier: Programming Language :: Python :: 3.8
Classifier: Programming Language :: Python :: 3.9
Requires-Dist: apache-airflow-providers-telegram (>=1.0.2,<2.0.0)
Requires-Dist: requests (>=2.25.1,<3.0.0)
Requires-Dist: requests-ntlm (>=1.1.0,<2.0.0)
Requires-Dist: zeep (>=4.0.0,<5.0.0)
Project-URL: Documentation, https://github.com/bintocher/qlikflow/blob/main/doc/readme.md
Project-URL: Repository, https://github.com/bintocher/qlikflow
